py_code_cleaner/__init__.py
py_code_cleaner/py_code_cleaner.py
py_code_cleaner/cli/__init__.py
py_code_cleaner/cli/clean_py.py
py_code_cleaner/cli/clean_py_many.py
py_code_cleaner/cli/utils.py
py_code_cleaner-1.3.0.dist-info/LICENSE
py_code_cleaner-1.3.0.dist-info/METADATA
py_code_cleaner-1.3.0.dist-info/WHEEL
py_code_cleaner-1.3.0.dist-info/entry_points.txt
py_code_cleaner-1.3.0.dist-info/top_level.txt
py_code_cleaner-1.3.0.dist-info/RECORD
