Metadata-Version: 2.1
Name: py-code-cleaner
Version: 1.3.0
Summary: Small PyPI package which provides python code cleaning from comments, docstrings, annotations
Home-page: https://github.com/PasaOpasen/py-code-cleaner
Author: Demetry Pascal
Author-email: qtckpuhdsa@gmail.com
Maintainer: Demetry Pascal
License: MIT
Keywords: code,clean,comments,docstrings,annotations
Platform: UNKNOWN
Classifier: Programming Language :: Python :: 3.8
Classifier: License :: OSI Approved :: MIT License
Classifier: Operating System :: OS Independent
Classifier: Topic :: Software Development :: Libraries :: Python Modules
License-File: LICENSE
Requires-Dist: astunparse
Requires-Dist: typing-extensions
